onlynet_tasks/__init__.py
onlynet_tasks/server.py
onlynet_tasks-1.2.0.dist-info/licenses/LICENSE
onlynet_tasks-1.2.0.dist-info/METADATA
onlynet_tasks-1.2.0.dist-info/WHEEL
onlynet_tasks-1.2.0.dist-info/entry_points.txt
onlynet_tasks-1.2.0.dist-info/top_level.txt
onlynet_tasks-1.2.0.dist-info/RECORD
