Metadata-Version: 2.4
Name: onlynet-tasks
Version: 1.2.0
Summary: MCP server for PRD generation and task management with Cursor agents
Author-email: OnlyNet <contact@onlynet.dev>
License-Expression: MIT
Project-URL: Homepage, https://github.com/onlynet/onlynet-tasks
Project-URL: Bug Reports, https://github.com/onlynet/onlynet-tasks/issues
Project-URL: Source, https://github.com/onlynet/onlynet-tasks
Classifier: Development Status :: 4 - Beta
Classifier: Intended Audience :: Developers
Classifier: Topic :: Software Development :: Libraries :: Python Modules
Classifier: Programming Language :: Python :: 3
Classifier: Programming Language :: Python :: 3.8
Classifier: Programming Language :: Python :: 3.9
Classifier: Programming Language :: Python :: 3.10
Classifier: Programming Language :: Python :: 3.11
Classifier: Programming Language :: Python :: 3.12
Requires-Python: >=3.8
License-File: LICENSE
Requires-Dist: fastmcp>=2.7.0
Requires-Dist: pydantic>=2.0.0
Requires-Dist: typing-extensions>=4.0.0
Dynamic: license-file
